python_daraja/__init__.py
python_daraja/payment.py
python_daraja-1.2.4.dist-info/LICENSE
python_daraja-1.2.4.dist-info/METADATA
python_daraja-1.2.4.dist-info/WHEEL
python_daraja-1.2.4.dist-info/top_level.txt
python_daraja-1.2.4.dist-info/RECORD
