Metadata-Version: 2.1
Name: python-daraja
Version: 1.2.4
Summary: Python Wrapper for interacting with the Daraja MPESA Payments API
Home-page: https://github.com/WilliamOtieno/python-daraja
Author: William Otieno
Author-email: jimmywilliamotieno@gmail.com
License: UNKNOWN
Platform: UNKNOWN
Classifier: Programming Language :: Python :: 3
Classifier: License :: OSI Approved :: MIT License
Classifier: Operating System :: OS Independent
Requires-Python: >=3.7
License-File: LICENSE
